Metadata-Version: 1.1
Name: bitbank-client
Version: 0.1.0
Summary: bitbank-client is a python client (sync/async) library for bitbank api.
Home-page: https://github.com/10mohi6/bitbank-api-python-client
Author: 10mohi6
Author-email: 10.mohi.6.y@gmail.com
License: MIT
Keywords: bitbank
Platform: UNKNOWN
Classifier: Development Status :: 5 - Production/Stable
Classifier: Programming Language :: Python :: 3.6
Classifier: Intended Audience :: Developers
Classifier: Topic :: Software Development :: Build Tools
Classifier: License :: OSI Approved :: MIT License
